.gitignore
LICENSE
MANIFEST.in
README.md
pyproject.toml
requirements.txt
setup.cfg
setup.py
.github/workflows/github-pytest.yml
dist/oompy-1.3.4.tar.gz
dist/oompy-1.4.0.tar.gz
oompy/__init__.py
oompy/constants.py
oompy/oom.py
oompy/test_oom.py
oompy/units.py
oompy/utils.py
oompy.egg-info/PKG-INFO
oompy.egg-info/SOURCES.txt
oompy.egg-info/dependency_links.txt
oompy.egg-info/not-zip-safe
oompy.egg-info/requires.txt
oompy.egg-info/top_level.txt