Metadata-Version: 2.1
Name: oompy
Version: 1.4.1
Summary: Tools for working with physical units and quantities
Home-page: https://github.com/haykh/oompy
Author: morninbru
Author-email: haykh.astro@gmail.com
License: BSD 3-Clause License
Requires-Python: >=3.6
License-File: LICENSE
Requires-Dist: types-setuptools
Requires-Dist: numpy
Requires-Dist: scipy
